collectmd-0.1.7.dist-info/METADATA
collectmd-0.1.7.dist-info/WHEEL
collectmd-0.1.7.dist-info/entry_points.txt
collectmd-0.1.7.dist-info/licenses/LICENSE
collectmd/__init__.py
collectmd/cli.py
collectmd/core.py
mymarkdown/__init__.py
collectmd-0.1.7.dist-info/RECORD
