Metadata-Version: 2.1
Name: collectmd
Version: 0.1.7
Summary: Default template for PDM package
Keywords: markdown,collector,file management
Author-Email: =?utf-8?b?5qGC5ZyG?= <1176916155@qq.com>
License: MIT
Classifier: Programming Language :: Python :: 3
Classifier: License :: OSI Approved :: MIT License
Classifier: Operating System :: OS Independent
Project-URL: Homepage, https://github.com/lightlogic5/collectmd
Project-URL: Repository, https://github.com/lightlogic5/collectmd.git
Requires-Python: >=3.10
Requires-Dist: click>=8.0.0
Requires-Dist: twine>=6.0.1
Requires-Dist: build>=1.2.2.post1
